README.md
setup.py
zdgrab.py
zdgrab.egg-info/PKG-INFO
zdgrab.egg-info/SOURCES.txt
zdgrab.egg-info/dependency_links.txt
zdgrab.egg-info/entry_points.txt
zdgrab.egg-info/not-zip-safe
zdgrab.egg-info/requires.txt
zdgrab.egg-info/top_level.txt