Metadata-Version: 2.1
Name: zdgrab
Version: 4.1.0
Summary: Get attachments from Zendesk tickets.
Home-page: http://github.com/fprimex/zdgrab
Author: Brent Woodruff
Author-email: brent@fprimex.com
License: Apache
Keywords: zendesk attachment
Platform: UNKNOWN
Classifier: Development Status :: 5 - Production/Stable
Classifier: Intended Audience :: End Users/Desktop
Classifier: License :: OSI Approved :: Apache Software License
Classifier: Topic :: Utilities
